edwh_odoo_plugin/__about__.py
edwh_odoo_plugin/__init__.py
edwh_odoo_plugin/odoo_base.py
edwh_odoo_plugin/odoo_plugin.py
edwh_odoo_plugin/search.py
edwh_odoo_plugin/task_manager.py
edwh_odoo_plugin/text_search.py
edwh_odoo_plugin/user_debug.py
edwh_odoo_plugin/web_search_server.py
edwh_odoo_plugin-0.3.0.dist-info/METADATA
edwh_odoo_plugin-0.3.0.dist-info/WHEEL
edwh_odoo_plugin-0.3.0.dist-info/entry_points.txt
edwh_odoo_plugin-0.3.0.dist-info/RECORD
