Metadata-Version: 2.4
Name: edwh-odoo-plugin
Version: 0.3.0
Summary: Odoo (search) support plugin for EDWH tooling.
Project-URL: Documentation, https://github.com/educationwarehouse/odoo#readme
Project-URL: Issues, https://github.com/educationwarehouse/odoo/issues
Project-URL: Source, https://github.com/educationwarehouse/odoo
Author-email: Remco Boerma <remco.b@educationwarehouse.nl>, Robin van der Noord <robin.vdn@educationwarehouse.nl>
License-Expression: MIT
Keywords: edwh
Classifier: Development Status :: 4 - Beta
Classifier: Programming Language :: Python
Classifier: Programming Language :: Python :: 3.10
Classifier: Programming Language :: Python :: 3.11
Classifier: Programming Language :: Python :: 3.12
Classifier: Programming Language :: Python :: Implementation :: CPython
Classifier: Programming Language :: Python :: Implementation :: PyPy
Requires-Python: >=3.11
Requires-Dist: edwh
Requires-Dist: markdown2
Requires-Dist: openerp-proxy
Requires-Dist: python-dotenv
Provides-Extra: dev
Requires-Dist: black; extra == 'dev'
Requires-Dist: hatch; extra == 'dev'
Requires-Dist: python-semantic-release<8; extra == 'dev'
